include/ggml-alloc.h
include/ggml-backend.h
include/ggml-blas.h
include/ggml-cann.h
include/ggml-cpp.h
include/ggml-cpu.h
include/ggml-cuda.h
include/ggml-kompute.h
include/ggml-metal.h
include/ggml-opt.h
include/ggml-rpc.h
include/ggml-sycl.h
include/ggml-vulkan.h
include/ggml.h
include/gguf.h
include/whisper.h
lib/pkgconfig/whisper.pc
lib64/libggml-base.so
lib64/libggml.so
lib64/libwhisper.so
lib64/libwhisper.so.1
lib64/libwhisper.so.1.7.4
lib64/cmake/ggml/ggml-config.cmake
lib64/cmake/ggml/ggml-version.cmake
lib64/cmake/whisper/whisper-config.cmake
lib64/cmake/whisper/whisper-version.cmake
whisper_cpp/__init__.py
whisper_cpp/libggml-base.so
whisper_cpp/libggml-cpu.so
whisper_cpp/libggml-opencl.so
whisper_cpp/libggml.so
whisper_cpp/libwhisper.so
whisper_cpp/libwhisper.so.1
whisper_cpp/libwhisper.so.1.7.4
whisper_cpp/whisper.py
whisper_cpp_python_smr.libs/libOpenCL-28f1cefa.so.1.0.0
whisper_cpp_python_smr.libs/libgomp-a34b3233.so.1.0.0
whisper_cpp_python_smr-0.2.3.dist-info/METADATA
whisper_cpp_python_smr-0.2.3.dist-info/WHEEL
whisper_cpp_python_smr-0.2.3.dist-info/RECORD
whisper_cpp_python_smr-0.2.3.dist-info/licenses/LICENSE
