Metadata-Version: 2.2
Name: whisper_cpp_python_smr
Version: 0.2.3
Summary: A tiny wrapper around whisper.cpp
Requires-Python: >=3.11
